{"q+DBL6Ip/DUrNNhuYzaAOQ==":"mbr.jpg","gsjYRdHRUVZKKoL5D2DVIg==":"mbr.jpeg","Jvd/Hv+E6dzGxsxf1OSMGw==":"mbr-1.jpg","Rkh6VN1geuklqasa+Hps8w==":"mbr-2.jpg","OgtCKla7ZhzAplY/dXMFRQ==":"mbr-3.jpg","7cAX25vTViPzsEpxKtfgnw==":"mbr-4.jpg","Bzg68IuBcRh9sFO8XLZmEQ==":"mbr-5.jpg","3L8x5ialuZVROWzapuz4nA==":"mbr-6.jpg","5Yxz1Ro3xgEvJK27QZYsvA==":"mbr-1.jpeg","orRrDp0O7uYYPUWXMASTrg==":"mbr-2.jpeg","hNnJ/ah4jJ+gnKLIjKCM+Q==":"mbr-3.jpeg","8lvp9ISHPOav0iH8GHzE5A==":"mbr-596x397.jpg","MrZJ9e7tOrKJvNJDsAPubw==":"328297408-3571716666448152-3610688767284505492-n.jpg","5TRI3auHFT38x9tTgbvt4w==":"img-583.jpeg","Mh9DXlaeNZBNPpJkc8P0ZA==":"img-106.jpeg","oEHzaBYbgKHMg8L6n6NE5A==":"zrzut-ekranu-2023-08-2-o-11.11.22.png","tu6QLYe8pKLYGoPKImtkYg==":"img-95.jpeg","JmACMQKtMnclN/YuTpTCaw==":"img-842.jpeg","hYBE0Rnw0s2cOCBq5gidDQ==":"zrzut-ekranu-2023-08-2-o-11.27.28.png","X8kUJgBUOg7wAKrSGvMpnQ==":"zrzut-ekranu-2023-08-2-o-11.29.47.png","YDBbSQBgsI1fePCg0z9Nag==":"img-107.jpeg","VtILbAJnifWysBSIJsoNhg==":"logo_preview_rev-1-96x93.png","ZGHJURB/Wwi3dX8Ldhus6Q==":"zrzut%20ekranu%202023-08-2%20o%2011.29.47-992x716.png","O+IXTmHtLxE+4cml+k/Ybw==":"projekt%20bez%20nazwy-940x788.png","3mfGAvMa5f10RKCghnks8w==":"projekt%20bez%20nazwy-940x788.png","kgjPOku7eFlcW1pWSTwWTQ==":"zrzut%20ekranu%202023-08-7%20o%2014.06.01-1014x702.png","kcB5xx6QlxTeWo+ib+p7QA==":"zrzut%20ekranu%202023-08-7%20o%2014.06.01-1014x702.png","nVFlg2sYiKqs0ViBbXgd9w==":"zrzut%20ekranu%202023-08-7%20o%2014.06.01-1014x702.png","XEadUpLC9T8+U2ybzoulLQ==":"img-583-896x1195.jpg","Q3Iy98t36yM/pkqXwvrg8Q==":"background7.jpg","oRykAiO0rUD++7AmPeEwUg==":"background1.jpg","n1dx+NZv3qks526xC0hZ5Q==":"background13.jpg","AA7T8WnSg7/ih8eEvxNBGA==":"projekt%20bez%20nazwy-940x788.jpg","an60E2pjZBI9ufRAyhiIgQ==":"zrzut%20ekranu%202024-04-8%20o%2013.22.00-1650x1008.png","s+CY130Ju4EEVTXu49I9eg==":"emilka23-2000x1333.jpeg","riDBV84Lq6ojplpNIaLbpg==":"emilka15-2000x2463.jpeg","uAEhv+B25yDVGoWrPRlnow==":"emilka7-2000x3000.jpg","nO9S9SKYlOCTfCkWhYGOGw==":"emilka7-2000x3000.jpeg","bLOVJSfqtAhrBoAxblpE6w==":"emilka7-1-2000x3000.jpeg","LLoNq7qW0mufrGycVE7d+w==":"emilka7-2-2000x3000.jpeg","LNzRSBGGyOfkxRrDR3YPdQ==":"emilka7-3-2000x3000.jpeg","CrI77uE3mjqTKvPGlAm1jQ==":"emilka7-4-2000x3000.jpeg","St60Ky8W5jAnEyokS0Ck4Q==":"emilka7-5-2000x3000.jpeg","Se+AbYK8PtQERBQecfuchg==":"emilka7-6-2000x3000.jpeg","q20M69BWxgdku31UUD1aCw==":"emilka3-896x1123.jpeg","zfO40EHD7bTaxw7zF9oPCQ==":"emilka2-896x1396.jpeg","p7fdRClJdKf9mWyDqtfg9w==":"emilka2-1-896x1396.jpeg","PF5vMqJvG1xNpkoZ85karA==":"emilka3-1-896x1123.jpeg","42LKH/NljtKMBx5YWZmmsw==":"emilka3-2-896x1123.jpeg","M2sWORaAKe0G2qEjjVtghA==":"emilka2-2-896x1396.jpeg","ZifQyKyuFTkxEdWYoSFyuQ==":"emilka12-896x1344.jpeg","zR/lq3ZnISPYQp2/dsp7TA==":"emilka10-896x1203.jpeg","7OM2aR2a7KB4IijSdlzU/g==":"emilka22-896x1400.jpeg","60567f/A9n9+TJHr7vt0Eg==":"emilka19-896x1240.jpeg","Vb7GgbMoe0curpGYBParsg==":"background3.jpg","cj+B4MTNBQ1L7yXfxEkSow==":"emilka14-1536x1884.jpg","encEclU0GVuDTfdlV0bw5A==":"emilka14-1536x1884.jpeg"}